{
  "db_name": "PostgreSQL",
  "query": "\n                INSERT INTO inventory_logs (\n                    inventory_id, movement_type, quantity, unit_cost, reason, created_at\n                ) VALUES ($1, $2, $3, $4, $5, $6)\n                ",
  "describe": {
    "columns": [],
    "parameters": {
      "Left": [
        "Uuid",
        "Varchar",
        "Numeric",
        "Numeric",
        "Text",
        "Timestamptz"
      ]
    },
    "nullable": []
  },
  "hash": "429fbaefc31b2bd5d3d0f0f064b199d27e8f10281364c492a3b85ad1c9b6c0e4"
}
